pylook/__init__.py
pylook/_version.py
pylook/cbook.py
pylook/package_tools.py
pylook/static-data-manifest.txt
pylook/testing.py
pylook/units.py
pylook/calc/__init__.py
pylook/calc/basic.py
pylook/io/__init__.py
pylook/io/lookfiles.py
pylook-0.1.1.dist-info/LICENSE
pylook-0.1.1.dist-info/METADATA
pylook-0.1.1.dist-info/WHEEL
pylook-0.1.1.dist-info/top_level.txt
pylook-0.1.1.dist-info/zip-safe
pylook-0.1.1.dist-info/RECORD
