Metadata-Version: 2.1
Name: pylook
Version: 0.1.1
Summary: Tools for analysis of experimental rock mechanics data.
Home-page: https://github.com/leemangeophysicalllc/pylook
Author: John Leeman
Author-email: support@leemangeophysical.com
Maintainer: Leeman Geophysical LLC
Maintainer-email: support@leemangeophysical.com
License: BSD 3-Clause
Project-URL: Documentation, https://leemangeophysicalllc.github.io/pylook/
Project-URL: Release Notes, https://github.com/leemangeophysicalllc/pylook/releases
Project-URL: Bug Tracker, https://github.com/leemangeophysicalllc/pylook/issues
Project-URL: Source Code, https://github.com/leemangeophysicalllc/pylook
Keywords: geology,geophysics
Platform: any
Classifier: Programming Language :: Python
Classifier: Programming Language :: Python :: 3.6
Classifier: Programming Language :: Python :: 3.7
Classifier: Programming Language :: Python :: 3.8
Classifier: Programming Language :: Python :: 3.9
Classifier: Topic :: Scientific/Engineering
Classifier: Intended Audience :: Science/Research
Classifier: Operating System :: OS Independent
Classifier: License :: OSI Approved :: BSD License
Requires-Python: >=3.6
Requires-Dist: numpy (>=1.16.0)
Requires-Dist: pandas (>=0.22.0)
Requires-Dist: pint (>=0.10.1)
Requires-Dist: pooch (>=0.1)
Requires-Dist: importlib-metadata (>=1.0.0) ; python_version < "3.8"
Requires-Dist: importlib-resources (>=1.3.0) ; python_version < "3.9"
